dont_fret/__init__.py
dont_fret/__main__.py
dont_fret/__version__.py
dont_fret/_version.py
dont_fret/aggregation.py
dont_fret/burst_search.py
dont_fret/channel_kde.py
dont_fret/expr.py
dont_fret/fileIO.py
dont_fret/formatting.py
dont_fret/models.py
dont_fret/process.py
dont_fret/support.py
dont_fret/tmp.py
dont_fret/transform.py
dont_fret/utils.py
dont_fret/config/__init__.py
dont_fret/config/config.py
dont_fret/config/default.yaml
dont_fret/config/default_web.yaml
dont_fret/web/__init__.py
dont_fret/web/components.py
dont_fret/web/datamanager.py
dont_fret/web/local_cluster.py
dont_fret/web/main.py
dont_fret/web/methods.py
dont_fret/web/models.py
dont_fret/web/state.py
dont_fret/web/style.css
dont_fret/web/utils.py
dont_fret/web/widgets.py
dont_fret/web/bursts/__init__.py
dont_fret/web/bursts/components.py
dont_fret/web/bursts/page.py
dont_fret/web/bursts/select_count.vue
dont_fret/web/home/__init__.py
dont_fret/web/home/burst_settings.py
dont_fret/web/home/fret_tree.vue
dont_fret/web/home/info_cards.py
dont_fret/web/home/methods.py
dont_fret/web/home/page.py
dont_fret/web/trace/__init__.py
dont_fret/web/trace/page.py
dont_fret-0.2.1.dist-info/METADATA
dont_fret-0.2.1.dist-info/WHEEL
dont_fret-0.2.1.dist-info/entry_points.txt
dont_fret-0.2.1.dist-info/licenses/LICENSE
dont_fret-0.2.1.dist-info/RECORD
