Metadata-Version: 2.4
Name: dont-fret
Version: 0.2.1
Summary: Analyze confocal solution smFRET data
Project-URL: Source, https://github.com/Jhsmit/dont-fret/
Author-email: Jochem Smit <jhsmit@gmail.com>
License-Expression: MIT
License-File: LICENSE
Classifier: Development Status :: 4 - Beta
Classifier: Intended Audience :: Science/Research
Classifier: Programming Language :: Python :: 3.10
Classifier: Programming Language :: Python :: 3.11
Classifier: Programming Language :: Python :: 3.12
Requires-Python: >=3.10
Requires-Dist: altair
Requires-Dist: anywidget
Requires-Dist: click
Requires-Dist: dacite
Requires-Dist: numba>=0.56.4
Requires-Dist: numpy>=1.18.0
Requires-Dist: pandas>=1.5.3
Requires-Dist: phconvert
Requires-Dist: plotly
Requires-Dist: polars>=0.20.23
Requires-Dist: pyyaml>=6.0
Requires-Dist: solara>=1.19.0
Requires-Dist: tqdm>=4.64.1
Requires-Dist: typing-extensions>=4.4.0
Requires-Dist: vegafusion[embed]
Requires-Dist: vl-convert-python
Provides-Extra: docs
Requires-Dist: mkdocs-gen-files>=0.4.0; extra == 'docs'
Requires-Dist: mkdocs-literate-nav>=0.5.0; extra == 'docs'
Requires-Dist: mkdocs-material>=8.5.11; extra == 'docs'
Requires-Dist: mkdocs>=1.4.2; extra == 'docs'
Requires-Dist: mkdocstrings[python]>=0.19.1; extra == 'docs'
Requires-Dist: pygments>=2.13.0; extra == 'docs'
Provides-Extra: plot
Requires-Dist: kdepy; extra == 'plot'
Requires-Dist: matplotlib; extra == 'plot'
Provides-Extra: test
Requires-Dist: pytest-asyncio; extra == 'test'
Requires-Dist: pytest-ipywidgets[solara]; extra == 'test'
Requires-Dist: pytest-playwright>=0.3.3; extra == 'test'
Requires-Dist: pytest>=7.2.0; extra == 'test'
